{
  "SP": "SP",
  "NASA": "NASA",
  "VA": "VA",
  "JPL": "JPL",
  "MSSS": "MSSS",
  "ARMD": "ARMD",
  "DC": "DC",
  "NPR": "NPR",
  "SEMP": "SEMP",
  "CM": "CM",
  "SOW": "SOW",
  "HSI": "HSI",
  "SE": "SE",
  "DRM": "DRM",
  "PBS": "PBS",
  "TRL": "TRL",
  "TMA": "TMA",
  "TA": "TA",
  "CAIB": "CAIB",
  "NIAT": "NIAT",
  "OCE": "OCE",
  "CJ": "CJ",
  "HQ": "HQ",
  "NEN": "NEN",
  "HDBK": "HDBK",
  "PP": "PP",
  "FIGURE": "FIGURE",
  "DM": "DM",
  "TABLE": "TABLE",
  "THE": "THE",
  "ORR": "ORR",
  "SIR": "SIR",
  "SDR": "SDR",
  "CDR": "CDR",
  "DR": "DR",
  "PDR": "PDR",
  "SRR": "SRR",
  "DRR": "DRR",
  "MCR": "MCR",
  "TP": "TP",
  "INCOSE": "INCOSE",
  "MOE": "MOE",
  "KDP": "KDP",
  "MDAA": "MDAA",
  "MDR": "MDR",
  "PRR": "PRR",
  "ASM": "ASM",
  "SAR": "SAR",
  "SRB": "SRB",
  "FRR": "FRR",
  "LV": "LV",
  "LRR": "LRR",
  "FA": "FA",
  "FAD": "FAD",
  "CERR": "CERR",
  "MRR": "MRR",
  "SMSR": "SMSR",
  "PFAR": "PFAR",
  "PLAR": "PLAR",
  "III": "III",
  "II": "II",
  "PM": "PM",
  "PMC": "PMC",
  "IT": "IT",
  "SPACE": "SPACE",
  "FLIGHT": "FLIGHT",
  "RFP": "RFP",
  "AO": "AO",
  "PSR": "PSR",
  "PIR": "PIR",
  "PRE": "PRE",
  "PHASE": "PHASE",
  "ROM": "ROM",
  "AND": "AND",
  "STD": "STD",
  "WBS": "WBS",
  "PUB": "PUB",
  "FIPS": "FIPS",
  "OMB": "OMB",
  "ABC": "ABC",
  "LCC": "LCC",
  "DESIGN": "DESIGN",
  "PI": "PI",
  "FINAL": "FINAL",
  "TEST": "TEST",
  "LAUNCH": "LAUNCH",
  "SYSTEM": "SYSTEM",
  "NPD": "NPD",
  "LEO": "LEO",
  "GEO": "GEO",
  "MSFC": "MSFC",
  "MA": "MA",
  "CE": "CE",
  "LSE": "LSE",
  "RFA": "RFA",
  "RID": "RID",
  "ISS": "ISS",
  "HST": "HST",
  "SLS": "SLS",
  "JWST": "JWST",
  "JIMO": "JIMO",
  "MPCV": "MPCV",
  "MER": "MER",
  "MRO": "MRO",
  "MIDES": "MIDES",
  "MEDLI": "MEDLI",
  "SAGE": "SAGE",
  "ARES": "ARES",
  "ESSP": "ESSP",
  "PA": "PA",
  "MISSE": "MISSE",
  "SMEX": "SMEX",
  "GAS": "GAS",
  "EV": "EV",
  "STORRM": "STORRM",
  "ALHAT": "ALHAT",
  "IRVE": "IRVE",
  "ELV": "ELV",
  "ID": "ID",
  "CD": "CD",
  "DGA": "DGA",
  "KEYS": "KEYS",
  "NOTE": "NOTE",
  "RF": "RF",
  "NGO": "NGO",
  "TBD": "TBD",
  "VS": "VS",
  "OF": "OF",
  "TVC": "TVC",
  "OSMA": "OSMA",
  "OCHMO": "OCHMO",
  "KDR": "KDR",
  "IRD": "IRD",
  "PRD": "PRD",
  "SRD": "SRD",
  "DOD": "DOD",
  "DODAF": "DODAF",
  "COTS": "COTS",
  "NSTS": "NSTS",
  "QA": "QA",
  "FMEA": "FMEA",
  "ILS": "ILS",
  "GSE": "GSE",
  "GROUND": "GROUND",
  "KSC": "KSC",
  "NDE": "NDE",
  "HWIL": "HWIL",
  "HITL": "HITL",
  "UFE": "UFE",
  "TYPES": "TYPES",
  "OTS": "OTS",
  "MOU": "MOU",
  "ITA": "ITA",
  "EVM": "EVM",
  "BCWS": "BCWS",
  "TPM": "TPM",
  "CCB": "CCB",
  "IWG": "IWG",
  "ICP": "ICP",
  "ICD": "ICD",
  "IDD": "IDD",
  "RISK": "RISK",
  "ITAR": "ITAR",
  "CRM": "CRM",
  "RM": "RM",
  "RIDM": "RIDM",
  "EIA": "EIA",
  "SAE": "SAE",
  "CSA": "CSA",
  "CMO": "CMO",
  "CI": "CI",
  "CHANGE": "CHANGE",
  "NORMAL": "NORMAL",
  "CR": "CR",
  "SBU": "SBU",
  "IPT": "IPT",
  "CPI": "CPI",
  "DATA": "DATA",
  "CER": "CER",
  "AADL": "AADL",
  "AD": "AD",
  "AIAA": "AIAA",
  "ASME": "ASME",
  "ASQ": "ASQ",
  "CEQ": "CEQ",
  "CHSIP": "CHSIP",
  "COSPAR": "COSPAR",
  "DDT": "DDT",
  "EDL": "EDL",
  "EEE": "EEE",
  "EFFBD": "EFFBD",
  "EMC": "EMC",
  "EMI": "EMI",
  "EO": "EO",
  "EOM": "EOM",
  "FAR": "FAR",
  "FCA": "FCA",
  "FFBD": "FFBD",
  "FM": "FM",
  "FMR": "FMR",
  "FTE": "FTE",
  "GOTS": "GOTS",
  "GSFC": "GSFC",
  "HCD": "HCD",
  "HF": "HF",
  "HSIP": "HSIP",
  "IEEE": "IEEE",
  "ISO": "ISO",
  "IV": "IV",
  "IVHM": "IVHM",
  "JCL": "JCL",
  "KBSI": "KBSI",
  "KPP": "KPP",
  "MBSE": "MBSE",
  "MEL": "MEL",
  "MODAF": "MODAF",
  "MOP": "MOP",
  "MOTS": "MOTS",
  "MRB": "MRB",
  "NEPA": "NEPA",
  "NFS": "NFS",
  "NID": "NID",
  "NOA": "NOA",
  "NOAA": "NOAA",
  "NODIS": "NODIS",
  "NRC": "NRC",
  "OCIO": "OCIO",
  "OCL": "OCL",
  "OWL": "OWL",
  "PCA": "PCA",
  "NSC": "NSC",
  "PD": "PD",
  "PKI": "PKI",
  "PPD": "PPD",
  "PRA": "PRA",
  "QVT": "QVT",
  "RACI": "RACI",
  "REC": "REC",
  "RMA": "RMA",
  "RUL": "RUL",
  "DOE": "DOE",
  "SI": "SI",
  "SMA": "SMA",
  "SME": "SME",
  "SRS": "SRS",
  "STI": "STI",
  "STS": "STS",
  "TBR": "TBR",
  "TRR": "TRR",
  "UML": "UML",
  "WYE": "WYE",
  "XMI": "XMI",
  "XML": "XML",
  "OR": "OR",
  "XYZ": "XYZ",
  "NOT": "NOT",
  "HOW": "HOW",
  "WHAT": "WHAT",
  "LDR": "LDR",
  "TPS": "TPS",
  "PTRS": "PTRS",
  "TRA": "TRA",
  "TRAR": "TRAR",
  "MPS": "MPS",
  "LH": "LH",
  "US": "US",
  "RCS": "RCS",
  "FS": "FS",
  "TVCS": "TVCS",
  "APU": "APU",
  "DH": "DH",
  "GN": "GN",
  "EPS": "EPS",
  "EGSE": "EGSE",
  "CLV": "CLV",
  "MPTA": "MPTA",
  "GVT": "GVT",
  "STA": "STA",
  "DTF": "DTF",
  "VTF": "VTF",
  "RRF": "RRF",
  "HFE": "HFE",
  "THIS": "THIS",
  "NO": "NO",
  "YES": "YES",
  "ITS": "ITS",
  "FOR": "FOR",
  "PLAN": "PLAN",
  "COR": "COR",
  "AL": "AL",
  "CRC": "CRC",
  "QMS": "QMS",
  "EAAI": "EAAI",
  "DAU": "DAU",
  "NIST": "NIST",
  "CEI": "CEI",
  "HIDH": "HIDH",
  "IEC": "IEC",
  "CFR": "CFR",
  "NJ": "NJ",
  "JSC": "JSC",
  "GEVS": "GEVS",
  "MIL": "MIL",
  "CEH": "CEH",
  "CSB": "CSB",
  "AECA": "AECA",
  "ANSI": "ANSI",
  "NF": "NF",
  "DAA": "DAA",
  "LARC": "LARC",
  "LPR": "LPR",
  "CCSDS": "CCSDS",
  "GEIA": "GEIA",
  "TOR": "TOR",
  "NDIA": "NDIA",
  "IBM": "IBM",
  "BPMN": "BPMN",
  "STPM": "STPM",
  "SSEE": "SSEE",
  "SEARI": "SEARI",
  "MIT": "MIT",
  "SECESA": "SECESA",
  "CA": "CA",
  "DAG": "DAG",
  "DLA": "DLA",
  "DDSM": "DDSM",
  "DTIC": "DTIC",
  "MD": "MD",
  "SD": "SD",
  "TR": "TR",
  "FAA": "FAA",
  "HFDS": "HFDS",
  "USA": "USA",
  "AB": "AB",
  "CMMI": "CMMI",
  "SEI": "SEI",
  "CMU": "CMU",
  "SR": "SR",
  "VHDL": "VHDL",
  "SELI": "SELI",
  "AP": "AP",
  "TS": "TS",
  "ITU": "ITU",
  "ODP": "ODP",
  "UK": "UK",
  "IMDC": "IMDC",
  "CORE": "CORE",
  "FL": "FL",
  "ISPE": "ISPE",
  "SIM": "SIM",
  "SPIE": "SPIE",
  "MT": "MT",
  "CO": "CO",
  "EC": "EC",
  "REV": "REV",
  "HIDP": "HIDP",
  "TX": "TX",
  "TRS": "TRS",
  "NESC": "NESC",
  "TM": "TM",
  "RP": "RP",
  "OH": "OH",
  "IBR": "IBR",
  "NSS": "NSS",
  "NE": "NE",
  "JPR": "JPR",
  "HMTA": "HMTA",
  "NPI": "NPI",
  "APR": "APR",
  "ARC": "ARC",
  "MWI": "MWI",
  "WI": "WI",
  "EA": "EA",
  "SEB": "SEB",
  "NAS": "NAS",
  "NY": "NY",
  "OOSEM": "OOSEM",
  "PMI": "PMI",
  "LA": "LA",
  "UPDM": "UPDM",
  "SMC": "SMC",
  "SECY": "SECY",
  "NUREG": "NUREG",
  "IDA": "IDA"
}